m365_extra/__init__.py
m365_extra/__main__.py
m365_extra/_version.py
m365_extra/calendar.py
m365_extra/drive.py
m365_extra/event.py
m365_extra/get.py
m365_extra/group.py
m365_extra/request.py
m365_extra/settings.py
m365_extra/site.py
m365_extra/upload.py
m365_extra/user.py
m365_extra-1.0.1.dist-info/licenses/LICENSE.txt
m365_extra-1.0.1.dist-info/METADATA
m365_extra-1.0.1.dist-info/WHEEL
m365_extra-1.0.1.dist-info/entry_points.txt
m365_extra-1.0.1.dist-info/top_level.txt
m365_extra-1.0.1.dist-info/RECORD
