Metadata-Version: 2.4
Name: m365-extra
Version: 1.0.1
Summary: Extra tools to interact with Microsoft M365 tenants.
Author-email: Sébastien Hocquet <seb@ipamo.net>
Project-URL: Homepage, https://gitlab.com/ipamo/m365-extra
Project-URL: Bug Tracker, https://gitlab.com/ipamo/m365-extra/issues
Requires-Python: >=3.11.2
License-File: LICENSE.txt
Requires-Dist: zut[default]>=2.1.1
Requires-Dist: msal>=1.31.1
Dynamic: license-file
